LICENSE.md
README.md
setup.py
aes_ecb_pkcs5/__init__.py
aes_ecb_pkcs5/aes_ecb_pkcs5.py
aes_ecb_pkcs5.egg-info/PKG-INFO
aes_ecb_pkcs5.egg-info/SOURCES.txt
aes_ecb_pkcs5.egg-info/dependency_links.txt
aes_ecb_pkcs5.egg-info/not-zip-safe
aes_ecb_pkcs5.egg-info/requires.txt
aes_ecb_pkcs5.egg-info/top_level.txt
aes_ecb_pkcs5/tests/__init__.py
aes_ecb_pkcs5/tests/test_aes_ecb_cipher.py