Metadata-Version: 2.1
Name: aes-ecb-pkcs5
Version: 0.0.1a0
Summary: AES/ECB/PKCS5 cipher encryption/decryption using python3 standard library.
Home-page: https://github.com/EverWinter23/aes-ecb-pkcs5
Author: Rishabh Mehta
Author-email: eternal.blizzard23@gmail.com
License: UNKNOWN
Keywords: aes ecb pkcs5 encryption decryption java aes-ecb
Platform: any
Classifier: Programming Language :: Python :: 3.7
Classifier: License :: OSI Approved :: Apache Software License
Classifier: Operating System :: OS Independent
Provides-Extra: test
Provides-Extra: dev
License-File: LICENSE.md
